bitcoin/__init__.py
bitcoin/address_listener/__init__.py
bitcoin/address_listener/address_listener.py
bitcoin/address_listener/simple_address_listener.py
bitcoin/models/__init__.py
bitcoin/models/address_tx_data.py
bitcoin/tests/__init__.py
bitcoin/tests/test_address_listener.py
bitcoin/tests/test_bitcoin_rpc.py
bitcoin/tests/test_bitcoin_utils.py
bitcoin/tests/data/__init__.py
bitcoin/tests/data/transactions.py
bitcoin/tx_extractors/__init__.py
bitcoin/tx_extractors/abstract_extractor.py
bitcoin/tx_extractors/bitcoin_rpc.py
bitcoin/tx_extractors/default.py
bitcoin/tx_extractors/mempool.py
bitcoin/tx_listener/__init__.py
bitcoin/tx_listener/abstract_tx_listener.py
bitcoin/tx_listener/zmq_listener.py
bitcoin/utils/__init__.py
bitcoin/utils/benchmark.py
bitcoin/utils/bitcoin_rpc.py
bitcoin/utils/bitcoin_utils.py
bitcoin/utils/constants.py
bitcoin/utils/context_aware_logging.py
bitcoin/utils/inscription_utils.py
bitcoinwatcher-2.18.dist-info/licenses/LICENSE
bitcoinwatcher-2.18.dist-info/METADATA
bitcoinwatcher-2.18.dist-info/WHEEL
bitcoinwatcher-2.18.dist-info/top_level.txt
bitcoinwatcher-2.18.dist-info/RECORD
