Metadata-Version: 2.4
Name: bitcoinwatcher
Version: 2.18
Summary: bitcoinwatcher is a Python library that implements a ZMQ subscriber and provides abstractions to build custom address watchers. This library is designed to make it easy for developers to monitor Bitcoin addresses and react to changes in their state.
Author: twosatsmaxi
License:                                  Apache License
Project-URL: Homepage, https://github.com/twosatsmaxi/watcher
Keywords: bitcoin,blockchain,ZMQ,subscriber,address watcher,bitcoin,listener,library
Classifier: Intended Audience :: Developers
Classifier: License :: OSI Approved :: MIT License
Classifier: Programming Language :: Python :: 3.10
Classifier: Programming Language :: Python :: 3.11
Classifier: Programming Language :: Python :: Implementation :: CPython
Classifier: Operating System :: OS Independent
Classifier: Topic :: Software Development :: Libraries :: Python Modules
Requires-Python: >=3.10
License-File: LICENSE
Requires-Dist: requests~=2.31.0
Requires-Dist: certifi==2024.2.2
Requires-Dist: charset-normalizer==3.3.2
Requires-Dist: idna==3.7
Requires-Dist: pyzmq==25.1.2
Requires-Dist: requests==2.31.0
Requires-Dist: urllib3==2.2.1
Requires-Dist: bitcoinlib==0.7.4
Requires-Dist: ordipool==1.2.0
Requires-Dist: pyzmq==25.1.2
Requires-Dist: python-bitcoinrpc-2sat==1.0.1
Requires-Dist: pytz~=2024.2
Requires-Dist: colorlog~=6.9.0
Dynamic: license-file
